moniplot/__init__.py
moniplot/biweight.py
moniplot/digitized_biweight.py
moniplot/draw_detector.py
moniplot/draw_geo.py
moniplot/draw_hist.py
moniplot/draw_image.py
moniplot/draw_lines.py
moniplot/draw_multi.py
moniplot/draw_qhist.py
moniplot/draw_time_serie.py
moniplot/draw_trend.py
moniplot/image_to_xarray.py
moniplot/mon_plot.py
moniplot/tol_colors.py
moniplot/unbiased_std.py
moniplot/Data/saa_region.yaml
moniplot/lib/__init__.py
moniplot/lib/fig_info.py
moniplot/lib/saa_region.py
moniplot-1.4.0.dist-info/METADATA
moniplot-1.4.0.dist-info/WHEEL
moniplot-1.4.0.dist-info/licenses/LICENSE
moniplot-1.4.0.dist-info/RECORD
