Metadata-Version: 2.4
Name: moniplot
Version: 1.4.0
Summary: a Python data visualization library for (satellite) instrument monitoring
Project-URL: homepage, https://github.com/rmvanhees/moniplot
Project-URL: documentation, https://moniplot.readthedocs.io/en/latest/
Project-URL: Issue tracker, https://github.com/rmvanhees/moniplot/issues
Author-email: Richard van Hees <R.M.van.Hees@sron.nl>, Paul Tol <P.J.J.Tol@sron.nl>
License-Expression: Apache-2.0
License-File: LICENSE
Classifier: Development Status :: 5 - Production/Stable
Classifier: Intended Audience :: Developers
Classifier: Intended Audience :: Science/Research
Classifier: Operating System :: OS Independent
Classifier: Programming Language :: Python :: 3 :: Only
Classifier: Programming Language :: Python :: 3.10
Classifier: Programming Language :: Python :: 3.11
Classifier: Programming Language :: Python :: 3.12
Classifier: Programming Language :: Python :: 3.13
Classifier: Topic :: Scientific/Engineering :: Atmospheric Science
Classifier: Topic :: Scientific/Engineering :: Image Processing
Classifier: Topic :: Scientific/Engineering :: Visualization
Requires-Python: >=3.10
Requires-Dist: cartopy>0.21
Requires-Dist: h5py>=3.9
Requires-Dist: matplotlib>=3.7
Requires-Dist: numpy>=1.25
Requires-Dist: tomli>=1; python_version < '3.11'
Requires-Dist: typing-extensions; python_version < '3.11'
Requires-Dist: xarray>=2023.3
